{"lat":-10.5,"lon":-40.25,"programs":["sota"],"count":8,"references":[{"code":"PY6/CN-060","program":"sota","name":"Serra da Jacobina","coordinates":[-40.2106,-10.3664]},{"code":"PY6/CN-066","program":"sota","name":"Serra da Boa Vista","coordinates":[-40.2492,-10.2606]},{"code":"PY6/CN-218","program":"sota","name":"Serra do Anjo","coordinates":[-40.1114,-10.3719]},{"code":"PY6/CN-223","program":"sota","name":"Serra da Umburana","coordinates":[-40.1136,-10.4483]},{"code":"PY6/CN-226","program":"sota","name":"Serra da Tiririca","coordinates":[-40.0797,-10.3453]},{"code":"PY6/CN-230","program":"sota","name":"Morro da Rocinha","coordinates":[-40.1669,-10.4306]},{"code":"PY6/CN-234","program":"sota","name":"Morro da Viúva","coordinates":[-40.1756,-10.4403]},{"code":"PY6/CN-264","program":"sota","name":"Serra do Anjo","coordinates":[-40.1111,-10.3439]}]}