{"lat":-22,"lon":-42.5,"programs":["sota"],"count":25,"references":[{"code":"PY1/CC-001","program":"sota","name":"PY1/CC-001","coordinates":[-42.461,-21.9344]},{"code":"PY1/CC-008","program":"sota","name":"Pedra do Borrão","coordinates":[-42.452,-21.9895]},{"code":"PY1/CC-009","program":"sota","name":"Serra do Prata","coordinates":[-42.4873,-21.8488]},{"code":"PY1/CC-010","program":"sota","name":"Serra São Martinho","coordinates":[-42.3327,-21.98]},{"code":"PY1/CC-011","program":"sota","name":"PY1/CC-011","coordinates":[-42.3501,-21.9908]},{"code":"PY1/CC-012","program":"sota","name":"PY1/CC-012","coordinates":[-42.4084,-21.9716]},{"code":"PY1/CC-013","program":"sota","name":"PY1/CC-013","coordinates":[-42.3795,-21.9772]},{"code":"PY1/CC-014","program":"sota","name":"Serra do Beirute","coordinates":[-42.416,-21.9486]},{"code":"PY1/CC-016","program":"sota","name":"PY1/CC-016","coordinates":[-42.3241,-21.8873]},{"code":"PY1/CC-017","program":"sota","name":"PY1/CC-017","coordinates":[-42.3979,-21.9096]},{"code":"PY1/CC-019","program":"sota","name":"PY1/CC-019","coordinates":[-42.4468,-21.8701]},{"code":"PY1/CC-020","program":"sota","name":"Serra do Vigário","coordinates":[-42.4029,-21.957]},{"code":"PY1/CC-022","program":"sota","name":"PY1/CC-022","coordinates":[-42.3213,-21.9444]},{"code":"PY1/CC-023","program":"sota","name":"PY1/CC-023","coordinates":[-42.412,-21.8507]},{"code":"PY1/CC-024","program":"sota","name":"PY1/CC-024","coordinates":[-42.3684,-21.8025]},{"code":"PY1/CC-026","program":"sota","name":"PY1/CC-026","coordinates":[-42.2767,-21.8819]},{"code":"PY1/CC-027","program":"sota","name":"PY1/CC-027","coordinates":[-42.2905,-21.7621]},{"code":"PY1/CC-036","program":"sota","name":"PY1/CC-036","coordinates":[-42.488,-21.8272]},{"code":"PY1/CC-037","program":"sota","name":"Serra da Laje","coordinates":[-42.4098,-21.8099]},{"code":"PY1/CC-038","program":"sota","name":"Serra do Português","coordinates":[-42.4259,-21.8023]},{"code":"PY1/CC-040","program":"sota","name":"PY1/CC-040","coordinates":[-42.2745,-21.9471]},{"code":"PY1/CC-041","program":"sota","name":"Serra das Águas Quentes","coordinates":[-42.2582,-21.8869]},{"code":"PY1/CC-042","program":"sota","name":"PY1/CC-042","coordinates":[-42.3551,-21.7746]},{"code":"PY1/CC-047","program":"sota","name":"PY1/CC-047","coordinates":[-42.2738,-21.8268]},{"code":"PY1/CC-048","program":"sota","name":"PY1/CC-048","coordinates":[-42.4094,-21.7852]}]}