{"lat":-22.75,"lon":16.25,"programs":["sota"],"count":6,"references":[{"code":"V5/KH-164","program":"sota","name":"V5/KH-164","coordinates":[16.292,-22.5791]},{"code":"V5/KH-165","program":"sota","name":"V5/KH-165","coordinates":[16.2791,-22.6478]},{"code":"V5/KH-169","program":"sota","name":"V5/KH-169","coordinates":[16.3506,-22.605]},{"code":"V5/KH-175","program":"sota","name":"V5/KH-175","coordinates":[16.3775,-22.5466]},{"code":"V5/KH-176","program":"sota","name":"V5/KH-176","coordinates":[16.3395,-22.5661]},{"code":"V5/KH-192","program":"sota","name":"V5/KH-192","coordinates":[16.3033,-22.6803]}]}