{"lat":-25.5,"lon":-48.25,"programs":["pota","sota"],"count":6,"references":[{"code":"BR-0078","program":"pota","name":"Superagüi National Conservation Area","coordinates":[-48.1558,-25.3314]},{"code":"PY5/PA-083","program":"sota","name":"PY5/PA-083","coordinates":[-48.192,-25.2723]},{"code":"PY5/PA-108","program":"sota","name":"Morro do Costa","coordinates":[-48.1149,-25.2523]},{"code":"PY5/PA-110","program":"sota","name":"Morro do Canudal","coordinates":[-48.1961,-25.3312]},{"code":"PY5/PA-114","program":"sota","name":"Morro da Colônia","coordinates":[-48.2392,-25.4141]},{"code":"PY5/PA-117","program":"sota","name":"Morro do Superagui","coordinates":[-48.2215,-25.3857]}]}