{"lat":-27.75,"lon":-49,"programs":["sota"],"count":8,"references":[{"code":"PP5/GF-034","program":"sota","name":"PP5/GF-034","coordinates":[-48.9598,-27.5594]},{"code":"PP5/GF-040","program":"sota","name":"PP5/GF-040","coordinates":[-48.9772,-27.528]},{"code":"PP5/GF-042","program":"sota","name":"Pico da Bandeira","coordinates":[-48.9722,-27.5869]},{"code":"PP5/GF-054","program":"sota","name":"PP5/GF-054","coordinates":[-48.778,-27.739]},{"code":"PP5/GF-055","program":"sota","name":"Morro Grande da Varginha","coordinates":[-48.8448,-27.625]},{"code":"PP5/GF-062","program":"sota","name":"Morro do Matias","coordinates":[-48.7749,-27.5936]},{"code":"PP5/GF-085","program":"sota","name":"Santa Filomena","coordinates":[-48.7802,-27.5458]},{"code":"PP5/GF-096","program":"sota","name":"PP5/GF-096","coordinates":[-48.8049,-27.5023]}]}