{"lat":20,"lon":-104.5,"programs":["sota"],"count":14,"references":[{"code":"XE1/JL-197","program":"sota","name":"XE1/JL-197","coordinates":[-104.39639,20.24917]},{"code":"XE1/JL-247","program":"sota","name":"XE1/JL-247","coordinates":[-104.48695,20.20167]},{"code":"XE1/JL-269","program":"sota","name":"XE1/JL-269","coordinates":[-104.47399,20.23446]},{"code":"XE1/JL-290","program":"sota","name":"XE1/JL-290","coordinates":[-104.45054,20.11808]},{"code":"XE1/JL-311","program":"sota","name":"XE1/JL-311","coordinates":[-104.35945,20.10642]},{"code":"XE1/JL-319","program":"sota","name":"XE1/JL-319","coordinates":[-104.49891,20.02148]},{"code":"XE1/JL-412","program":"sota","name":"XE1/JL-412","coordinates":[-104.45231,20.01886]},{"code":"XE1/JL-413","program":"sota","name":"XE1/JL-413","coordinates":[-104.39734,20.16593]},{"code":"XE1/JL-425","program":"sota","name":"XE1/JL-425","coordinates":[-104.40643,20.06786]},{"code":"XE1/JL-428","program":"sota","name":"XE1/JL-428","coordinates":[-104.36599,20.08417]},{"code":"XE1/JL-461","program":"sota","name":"XE1/JL-461","coordinates":[-104.28134,20.21305]},{"code":"XE1/JL-485","program":"sota","name":"XE1/JL-485","coordinates":[-104.41084,20.05]},{"code":"XE1/JL-529","program":"sota","name":"XE1/JL-529","coordinates":[-104.37778,20.0288]},{"code":"XE1/JL-555","program":"sota","name":"XE1/JL-555","coordinates":[-104.26628,20.0436]}]}