{"lat":20.75,"lon":-100.25,"programs":["sota"],"count":9,"references":[{"code":"XE1/GJ-034","program":"sota","name":"XE1/GJ-034","coordinates":[-100.2466,20.97711]},{"code":"XE1/GJ-047","program":"sota","name":"XE1/GJ-047","coordinates":[-100.23385,20.95184]},{"code":"XE1/QT-002","program":"sota","name":"Cerro El Zamorano","coordinates":[-100.1807,20.93403]},{"code":"XE1/QT-012","program":"sota","name":"XE1/QT-012","coordinates":[-100.12834,20.93012]},{"code":"XE1/QT-018","program":"sota","name":"XE1/QT-018","coordinates":[-100.00391,20.98775]},{"code":"XE1/QT-068","program":"sota","name":"XE1/QT-068","coordinates":[-100.14126,20.78143]},{"code":"XE1/QT-069","program":"sota","name":"XE1/QT-069","coordinates":[-100.10678,20.82596]},{"code":"XE1/QT-072","program":"sota","name":"XE1/QT-072","coordinates":[-100.11429,20.77756]},{"code":"XE1/QT-086","program":"sota","name":"XE1/QT-086","coordinates":[-100.08787,20.77758]}]}