{"lat":21,"lon":-103.25,"programs":["sota"],"count":7,"references":[{"code":"XE1/JL-090","program":"sota","name":"XE1/JL-090","coordinates":[-103.03696,21.11327]},{"code":"XE2/ZC-157","program":"sota","name":"XE2/ZC-157","coordinates":[-103.011696,21.17735]},{"code":"XE2/ZC-163","program":"sota","name":"XE2/ZC-163","coordinates":[-103.06869,21.21314]},{"code":"XE2/ZC-346","program":"sota","name":"XE2/ZC-346","coordinates":[-103.189064,21.15708]},{"code":"XE2/ZC-348","program":"sota","name":"XE2/ZC-348","coordinates":[-103.21325,21.1054]},{"code":"XE2/ZC-350","program":"sota","name":"XE2/ZC-350","coordinates":[-103.16902,21.155138]},{"code":"XE2/ZC-355","program":"sota","name":"XE2/ZC-355","coordinates":[-103.18883,21.208939]}]}