{"lat":23,"lon":-100,"programs":["sota"],"count":14,"references":[{"code":"XE2/TM-027","program":"sota","name":"XE2/TM-027","coordinates":[-99.9055,23.17682]},{"code":"XE2/TM-032","program":"sota","name":"XE2/TM-032","coordinates":[-99.9189,23.19986]},{"code":"XE2/TM-033","program":"sota","name":"XE2/TM-033","coordinates":[-99.9013,23.08423]},{"code":"XE2/TM-036","program":"sota","name":"XE2/TM-036","coordinates":[-99.9132,23.12396]},{"code":"XE2/TM-038","program":"sota","name":"XE2/TM-038","coordinates":[-99.8894,23.10167]},{"code":"XE2/TM-041","program":"sota","name":"XE2/TM-041","coordinates":[-99.9552,23.11208]},{"code":"XE2/TM-051","program":"sota","name":"XE2/TM-051","coordinates":[-99.8868,23.08786]},{"code":"XE2/TM-061","program":"sota","name":"XE2/TM-061","coordinates":[-99.9764,23.07306]},{"code":"XE2/TM-075","program":"sota","name":"XE2/TM-075","coordinates":[-99.9969,23.13537]},{"code":"XE2/TM-080","program":"sota","name":"XE2/TM-080","coordinates":[-99.7932,23.22912]},{"code":"XE2/TM-088","program":"sota","name":"XE2/TM-088","coordinates":[-99.9057,23.02478]},{"code":"XE2/TM-091","program":"sota","name":"XE2/TM-091","coordinates":[-99.9499,23.00416]},{"code":"XE2/TM-154","program":"sota","name":"XE2/TM-154","coordinates":[-99.8413,23.10014]},{"code":"XE2/TM-179","program":"sota","name":"XE2/TM-179","coordinates":[-99.7711,23.1525]}]}