{"lat":28.5,"lon":-106.5,"programs":["sota"],"count":11,"references":[{"code":"XE2/CC-105","program":"sota","name":"XE2/CC-105","coordinates":[-106.4476,28.7108]},{"code":"XE2/CC-182","program":"sota","name":"XE2/CC-182","coordinates":[-106.4095,28.6355]},{"code":"XE2/CC-189","program":"sota","name":"XE2/CC-189","coordinates":[-106.4111,28.6789]},{"code":"XE2/CC-260","program":"sota","name":"XE2/CC-260","coordinates":[-106.3916,28.606]},{"code":"XE2/CC-353","program":"sota","name":"XE2/CC-353","coordinates":[-106.4668,28.675]},{"code":"XE2/CC-362","program":"sota","name":"XE2/CC-362","coordinates":[-106.2899,28.5279]},{"code":"XE2/CC-365","program":"sota","name":"XE2/CC-365","coordinates":[-106.2838,28.5143]},{"code":"XE2/CC-367","program":"sota","name":"XE2/CC-367","coordinates":[-106.3317,28.6441]},{"code":"XE2/CC-372","program":"sota","name":"XE2/CC-372","coordinates":[-106.306,28.6493]},{"code":"XE2/CC-382","program":"sota","name":"XE2/CC-382","coordinates":[-106.3275,28.5104]},{"code":"XE2/CC-480","program":"sota","name":"XE2/CC-480","coordinates":[-106.3728,28.7314]}]}