{"lat":32.75,"lon":-116.25,"programs":["sota"],"count":7,"references":[{"code":"W6/SD-356","program":"sota","name":"Carrizo Mountain","coordinates":[-116.0152,32.8252]},{"code":"W6/SD-357","program":"sota","name":"Eagle Benchmark","coordinates":[-116.002,32.9782]},{"code":"W6/SD-370","program":"sota","name":"2181","coordinates":[-116.0383,32.9892]},{"code":"W6/SD-376","program":"sota","name":"2140","coordinates":[-116.0139,32.9858]},{"code":"W6/SD-379","program":"sota","name":"2121","coordinates":[-116.062,32.9689]},{"code":"W6/SD-396","program":"sota","name":"Mine Benchmark","coordinates":[-116.1343,32.8318]},{"code":"W6/SD-428","program":"sota","name":"1401","coordinates":[-116.0129,32.9153]}]}