{"lat":35.5,"lon":-82.75,"programs":["pota","sota"],"count":8,"references":[{"code":"US-6853","program":"pota","name":"Thomas Wolfe Memorial State Historic Site","coordinates":[-82.5513,35.5975]},{"code":"US-6949","program":"pota","name":"Sandy Mush State Game Land","coordinates":[-82.6691,35.7047]},{"code":"W4C/CM-117","program":"sota","name":"Hayes Top","coordinates":[-82.7061,35.601]},{"code":"W4C/CM-125","program":"sota","name":"High Top","coordinates":[-82.6737,35.5898]},{"code":"W4C/CM-126","program":"sota","name":"Busbee Mountain","coordinates":[-82.5043,35.5217]},{"code":"W4C/CM-135","program":"sota","name":"Luther Knob","coordinates":[-82.6903,35.5908]},{"code":"W4C/CM-141","program":"sota","name":"Hanlon Mountain","coordinates":[-82.7368,35.6443]},{"code":"W4C/CM-156","program":"sota","name":"Scott Mountain","coordinates":[-82.6379,35.5267]}]}