{"lat":35.75,"lon":-116.75,"programs":["sota"],"count":7,"references":[{"code":"W6/ND-221","program":"sota","name":"Epaulet Peak","coordinates":[-116.5243,35.9727]},{"code":"W6/ND-245","program":"sota","name":"Desert Hound Peak","coordinates":[-116.6222,35.9624]},{"code":"W6/ND-294","program":"sota","name":"3809","coordinates":[-116.7486,35.7915]},{"code":"W6/ND-342","program":"sota","name":"3110","coordinates":[-116.542,35.8869]},{"code":"W6/ND-344","program":"sota","name":"3061","coordinates":[-116.5073,35.8672]},{"code":"W6/ND-353","program":"sota","name":"2867","coordinates":[-116.6419,35.7582]},{"code":"W6/ND-363","program":"sota","name":"Jubilee Mountain","coordinates":[-116.583,35.8976]}]}