{"lat":36.5,"lon":-2.75,"programs":["pota"],"count":6,"references":[{"code":"ES-0527","program":"pota","name":"Punta Entinas-Sabinar National Park","coordinates":[-2.6705,36.7029]},{"code":"ES-1488","program":"pota","name":"Charcones de Punta Entinas Wetland Reserve","coordinates":[-2.689,36.6941]},{"code":"ES-1489","program":"pota","name":"Laguna de la Gravera Wetland Reserve","coordinates":[-2.6434,36.7176]},{"code":"ES-1491","program":"pota","name":"Salinas de Cerrillos Wetland Reserve","coordinates":[-2.6673,36.7061]},{"code":"ES-2304","program":"pota","name":"Sur de Almería - Seco de los Olivos Natura 2000","coordinates":[-2.5009,36.647]},{"code":"ES-2305","program":"pota","name":"Fondos Marinos de Punta Entinas-Sabinar Natura 2000","coordinates":[-2.7007,36.6782]}]}