{"lat":37,"lon":127.25,"programs":["sota"],"count":14,"references":[{"code":"HL/GG-086","program":"sota","name":"쌍령산 (Ssangnyeongsan)","coordinates":[127.2747,37.1338]},{"code":"HL/GG-099","program":"sota","name":"구봉산 (Gubongsan)","coordinates":[127.3324,37.1282]},{"code":"HL/GG-107","program":"sota","name":"망이산 (Mangisan)","coordinates":[127.4895,37.0525]},{"code":"HL/GG-109","program":"sota","name":"마국산 (Maguksan)","coordinates":[127.4504,37.1475]},{"code":"HL/GG-113","program":"sota","name":"갈미봉 (Galmibong)","coordinates":[127.2856,37.2073]},{"code":"HL/GG-114","program":"sota","name":"국사봉 (Guksabong)","coordinates":[127.34,37.0752]},{"code":"HL/GG-118","program":"sota","name":"건지산 (Geonjisan)","coordinates":[127.3418,37.2086]},{"code":"HL/GG-136","program":"sota","name":"비봉산 (Bibongsan)","coordinates":[127.416,37.0893]},{"code":"HL/GG-145","program":"sota","name":"삼박골산 (Sambakgolsan)","coordinates":[127.4593,37.0442]},{"code":"HL/GG-148","program":"sota","name":"수정산 (Sujeongsan)","coordinates":[127.3487,37.1922]},{"code":"HL/GG-150","program":"sota","name":"대덕산 (Daedeoksan)","coordinates":[127.4113,37.1666]},{"code":"HL/GG-155","program":"sota","name":"노성산 (Noseongsan)","coordinates":[127.4992,37.1234]},{"code":"HL/GG-156","program":"sota","name":"수학산 (Suhaksan)","coordinates":[127.3693,37.2063]},{"code":"HL/GG-164","program":"sota","name":"머린골산 (Meoringolsan)","coordinates":[127.2772,37.0374]}]}