{"lat":38,"lon":-81,"programs":["pota","sota"],"count":4,"references":[{"code":"US-0695","program":"pota","name":"Gauley River National Recreation Area","coordinates":[-80.8898,38.2173]},{"code":"US-1807","program":"pota","name":"Carnifex Ferry Battlefield State Park","coordinates":[-80.9394,38.207]},{"code":"US-9755","program":"pota","name":"Summersville Lake State Park","coordinates":[-80.8554,38.2469]},{"code":"W8V/ML-012","program":"sota","name":"Panther Mountain","coordinates":[-80.9993,38.2448]}]}