{"lat":38,"lon":-86.5,"programs":["pota","sota"],"count":5,"references":[{"code":"US-2262","program":"pota","name":"O'Bannon Woods State Park","coordinates":[-86.2729,38.193]},{"code":"US-4203","program":"pota","name":"Harrison-Crawford State Forest","coordinates":[-86.2552,38.2011]},{"code":"US-10224","program":"pota","name":"Mouth of Blue River State Nature Preserve","coordinates":[-86.3105,38.1725]},{"code":"US-10225","program":"pota","name":"Post Oak-Cedar State Nature Preserve","coordinates":[-86.2736,38.1858]},{"code":"W9/IN-003","program":"sota","name":"Greenbrier Knob","coordinates":[-86.2836,38.2178]}]}