{"lat":41,"lon":-107,"programs":["pota","sota"],"count":8,"references":[{"code":"US-6130","program":"pota","name":"Encampment River Wilderness Area","coordinates":[-106.797,41.1295]},{"code":"US-6133","program":"pota","name":"Huston Park Wilderness Area","coordinates":[-106.911,41.1098]},{"code":"US-6134","program":"pota","name":"Indian Bathtubs Trail BLM Recreation Management Area","coordinates":[-106.765,41.2045]},{"code":"US-6136","program":"pota","name":"Encampment River Canyon BLM Recreation Management Area","coordinates":[-106.799,41.1591]},{"code":"W7Y/SW-020","program":"sota","name":"10561","coordinates":[-106.9356,41.0948]},{"code":"W7Y/SW-022","program":"sota","name":"Red Mountain","coordinates":[-106.9858,41.1383]},{"code":"W7Y/SW-056","program":"sota","name":"9860","coordinates":[-106.9386,41.0246]},{"code":"W7Y/SW-121","program":"sota","name":"8545","coordinates":[-106.803,41.1531]}]}