{"lat":42,"lon":-4.75,"programs":["pota"],"count":5,"references":[{"code":"ES-2267","program":"pota","name":"Camino Lebaniego Castellano National Recreation Trail","coordinates":[-4.54051,42.0077]},{"code":"ES-0418","program":"pota","name":"Lagunas del Canal de Castilla Natura 2000","coordinates":[-4.5494,42.1377]},{"code":"ES-0424","program":"pota","name":"Riberas del rio Carrion y afluentes Natura 2000","coordinates":[-4.5577,42.186]},{"code":"ES-0428","program":"pota","name":"Laguna de la Nava Natura 2000","coordinates":[-4.7454,42.0637]},{"code":"ES-1787","program":"pota","name":"Camino Natural Vía Verde del Tren Secundario de Castilla National Recreation Trail","coordinates":[-4.66211,42.0149]}]}