{"lat":42.5,"lon":24.25,"programs":["gma","sota"],"count":33,"references":[{"code":"LZM/SD-001","program":"gma","name":"Shiligarnika","coordinates":[24.488343,42.603128]},{"code":"LZM/SD-003","program":"gma","name":"Malkiya venets","coordinates":[24.308855,42.586649]},{"code":"LZM/SD-006","program":"gma","name":"Ursolitsa","coordinates":[24.288899,42.632266]},{"code":"LZM/SD-007","program":"gma","name":"Starmonas","coordinates":[24.31467,42.575384]},{"code":"LZM/SD-008","program":"gma","name":"Malkiya pop","coordinates":[24.333558,42.629548]},{"code":"LZM/SD-009","program":"gma","name":"Nevida","coordinates":[24.459386,42.626689]},{"code":"LZM/SD-010","program":"gma","name":"Zlatyuvitsa","coordinates":[24.254637,42.632869]},{"code":"LZM/SD-011","program":"gma","name":"Beliya kamak","coordinates":[24.40778,42.647376]},{"code":"LZM/SD-014","program":"gma","name":"Manzul","coordinates":[24.25086,42.617744]},{"code":"LZM/SD-015","program":"gma","name":"Omaritsa","coordinates":[24.490237,42.620874]},{"code":"LZM/SD-016","program":"gma","name":"Roshova mogila","coordinates":[24.321531,42.654691]},{"code":"LZM/SD-017","program":"gma","name":"Debeli rid","coordinates":[24.435782,42.64021]},{"code":"LZM/SD-018","program":"gma","name":"Boev shaman","coordinates":[24.339711,42.583813]},{"code":"LZM/SD-019","program":"gma","name":"Chumen","coordinates":[24.376216,42.679399]},{"code":"LZM/SD-021","program":"gma","name":"Lomaka","coordinates":[24.483536,42.58986]},{"code":"LZM/SD-023","program":"gma","name":"Klimash","coordinates":[24.307895,42.678492]},{"code":"LZM/SD-025","program":"gma","name":"Mrankov vrah","coordinates":[24.36524,42.661807]},{"code":"LZM/SD-026","program":"gma","name":"Panagyurska mandra","coordinates":[24.251563,42.604929]},{"code":"LZM/SD-027","program":"gma","name":"Krasta","coordinates":[24.459839,42.57204]},{"code":"LZM/SD-030","program":"gma","name":"Sveti Luka","coordinates":[24.331605,42.663709]},{"code":"LZM/SD-032","program":"gma","name":"Sveta Petka","coordinates":[24.374167,42.6389]},{"code":"LZM/SD-037","program":"gma","name":"Setcemeka","coordinates":[24.447799,42.58971]},{"code":"LZM/SD-046","program":"gma","name":"Ginder","coordinates":[24.455384,42.681043]},{"code":"LZM/ZT-009","program":"gma","name":"Pypa","coordinates":[24.376431,42.748966]},{"code":"LZM/ZT-016","program":"gma","name":"Dapkovoto kraishte","coordinates":[24.401236,42.729298]},{"code":"LZM/ZT-024","program":"gma","name":"Haiduk","coordinates":[24.428101,42.717948]},{"code":"LZM/ZT-029","program":"gma","name":"Diktepe","coordinates":[24.369307,42.726839]},{"code":"LZM/ZT-034","program":"gma","name":"Kaleto","coordinates":[24.35626,42.729834]},{"code":"LZM/ZT-041","program":"gma","name":"Cherni vrah","coordinates":[24.476981,42.715647]},{"code":"LZM/ZT-056","program":"gma","name":"Golyamata mogila","coordinates":[24.474192,42.701677]},{"code":"LZ/SG-001","program":"sota","name":"Bogdan","coordinates":[24.461,42.6075]},{"code":"LZ/SG-002","program":"sota","name":"Bunaya","coordinates":[24.323,42.5921]},{"code":"LZ/SG-005","program":"sota","name":"Bich","coordinates":[24.2878,42.618]}]}