{"lat":42.5,"lon":-76.25,"programs":["pota","sota"],"count":9,"references":[{"code":"US-5052","program":"pota","name":"Hewitt State Forest","coordinates":[-76.2215,42.743]},{"code":"US-5063","program":"pota","name":"Hoxie Gorge State Forest","coordinates":[-76.0713,42.5227]},{"code":"US-5093","program":"pota","name":"Baker School House State Forest","coordinates":[-76.0148,42.5745]},{"code":"US-5205","program":"pota","name":"Donahue Woods State Forest","coordinates":[-76.031,42.6605]},{"code":"US-5349","program":"pota","name":"Tuller Hill State Forest","coordinates":[-76.1291,42.5248]},{"code":"W2/WE-043","program":"sota","name":"2110","coordinates":[-76.1379,42.5438]},{"code":"W2/WE-046","program":"sota","name":"2030","coordinates":[-76.0854,42.7471]},{"code":"W2/WE-047","program":"sota","name":"1990","coordinates":[-76.0044,42.6383]},{"code":"W2/WE-050","program":"sota","name":"South Hill B","coordinates":[-76.0802,42.5725]}]}