{"lat":44,"lon":6,"programs":["pota","sota"],"count":24,"references":[{"code":"FR-7648","program":"pota","name":"montagne de gache - defile de pierre ecrite - rocher de dromont - le grand adroit Biological Reserve","coordinates":[6.02477,44.2458]},{"code":"FR-11722","program":"pota","name":"massif du siron - cretes du mouras et de la fubie - cretes du frigourias Biological Reserve","coordinates":[6.18942,44.1565]},{"code":"FR-11728","program":"pota","name":"la bleone et ses principaux affluents (les duyes, le galebre, le bes, le bouinenc) et leurs ripislves Biological Reserve","coordinates":[6.10634,44.0326]},{"code":"F/AM-362","program":"sota","name":"Sommet de Nibles","coordinates":[6.2193,44.24]},{"code":"F/AM-364","program":"sota","name":"Cloche de Barles","coordinates":[6.2303,44.2355]},{"code":"F/AM-366","program":"sota","name":"Crête de Géruen","coordinates":[6.1759,44.2201]},{"code":"F/AM-394","program":"sota","name":"Montagne de Mélan","coordinates":[6.1329,44.2107]},{"code":"F/AM-413","program":"sota","name":"La Bigue","coordinates":[6.1891,44.1448]},{"code":"F/AM-474","program":"sota","name":"Sommet de Cousson","coordinates":[6.2396,44.0537]},{"code":"F/AM-490","program":"sota","name":"Le Mouras","coordinates":[6.1877,44.1702]},{"code":"F/AM-496","program":"sota","name":"Les Vautes","coordinates":[6.0916,44.1744]},{"code":"F/AM-517","program":"sota","name":"La Chau","coordinates":[6.2287,44.1917]},{"code":"F/AM-526","program":"sota","name":"La Falle","coordinates":[6.0479,44.2346]},{"code":"F/AM-537","program":"sota","name":"Sommet du Ruth","coordinates":[6.0798,44.1037]},{"code":"F/AM-555","program":"sota","name":"Rochers de Saint Michel","coordinates":[6.0229,44.2102]},{"code":"F/AM-583","program":"sota","name":"Pic d'Oise","coordinates":[6.1389,44.0979]},{"code":"F/AM-611","program":"sota","name":"Sommet du Puy Haut","coordinates":[6.1222,44.0691]},{"code":"F/AM-621","program":"sota","name":"Le Grépon","coordinates":[6.0309,44.176]},{"code":"F/AM-625","program":"sota","name":"Brame-Faim","coordinates":[6.0574,44.0589]},{"code":"F/AM-630","program":"sota","name":"Cime des Usclats","coordinates":[6.0816,44.0509]},{"code":"F/AM-800","program":"sota","name":"Le Sabot Rocher","coordinates":[6.0732,44.2325]},{"code":"F/AM-814","program":"sota","name":"Campanelle","coordinates":[6.1491,44.1185]},{"code":"F/AM-819","program":"sota","name":"Rocher Neuf Heures","coordinates":[6.2493,44.0942]},{"code":"F/AM-820","program":"sota","name":"La Croix","coordinates":[6.2424,44.1026]}]}