{"lat":44.5,"lon":-1.5,"programs":["wwbota"],"count":12,"references":[{"code":"B/F-6816","program":"wwbota","name":"Cap-Ferret1","coordinates":[-1.250986,44.694007]},{"code":"B/F-6817","program":"wwbota","name":"Cap-Ferret2","coordinates":[-1.25882,44.659086]},{"code":"B/F-6818","program":"wwbota","name":"Cap-Ferret3","coordinates":[-1.259036,44.65827]},{"code":"B/F-6819","program":"wwbota","name":"Cap-Ferret4","coordinates":[-1.258875,44.656273]},{"code":"B/F-6820","program":"wwbota","name":"Cap-Ferret5","coordinates":[-1.258593,44.65587]},{"code":"B/F-6821","program":"wwbota","name":"Cap-Ferret5","coordinates":[-1.259319,44.65396]},{"code":"B/F-6822","program":"wwbota","name":"Cap-Ferret6","coordinates":[-1.259519,44.6397]},{"code":"B/F-6824","program":"wwbota","name":"Cap-Ferret7","coordinates":[-1.259633,44.638677]},{"code":"B/F-6825","program":"wwbota","name":"Cap-Ferret8","coordinates":[-1.256632,44.624855]},{"code":"B/F-6826","program":"wwbota","name":"Cap-Ferret9","coordinates":[-1.256172,44.623458]},{"code":"B/F-6827","program":"wwbota","name":"Cap-Ferret10","coordinates":[-1.256639,44.623339]},{"code":"B/F-6828","program":"wwbota","name":"Cap-Ferret11","coordinates":[-1.257062,44.623191]}]}