{"lat":45,"lon":21.25,"programs":["gma","pota","sota","wwbota"],"count":8,"references":[{"code":"YP/WC-013","program":"gma","name":"Dealul Verzi?or","coordinates":[21.49670029,45.12580109]},{"code":"RS-0037","program":"pota","name":"Vršačke planine Landscape Reserve","coordinates":[21.3968,45.1291]},{"code":"RS-0215","program":"pota","name":"Vršački park Natural Monument","coordinates":[21.3074,45.1192]},{"code":"RS-0155","program":"pota","name":"Mali Vršački rit Habitat Protection Area","coordinates":[21.3497,45.1616]},{"code":"YU/VO-001","program":"sota","name":"Gudurički vrh","coordinates":[21.41252,45.13711]},{"code":"YU/VO-002","program":"sota","name":"Vršački vrh (Lisičja glava)","coordinates":[21.37137,45.13975]},{"code":"YU/VO-004","program":"sota","name":"Đalu Veršišor (Dealul Verzișor)","coordinates":[21.49746,45.12603]},{"code":"B/YU-0009","program":"wwbota","name":"Vrsacki breg Bunkeri","coordinates":[21.3252,45.1214]}]}