{"lat":46.25,"lon":-79.5,"programs":["pota","sota","wwbota"],"count":5,"references":[{"code":"CA-1711","program":"pota","name":"Widdifield Forest Provincial Park","coordinates":[-79.3253,46.4473]},{"code":"VE3/NE-370","program":"sota","name":"VE3/NE-370","coordinates":[-79.3157,46.4389]},{"code":"VE3/NE-485","program":"sota","name":"VE3/NE-485","coordinates":[-79.2742,46.3564]},{"code":"B/CA-0006","program":"wwbota","name":"NORAD Complex","coordinates":[-79.416904,46.356065]},{"code":"B/CA-1098","program":"wwbota","name":"FRP LB42","coordinates":[-79.4166667,46.3333333]}]}