{"lat":46.5,"lon":5.5,"programs":["pota","sota"],"count":38,"references":[{"code":"FR-5395","program":"pota","name":"LA RENVERSURE Biological Reserve","coordinates":[5.577,46.6205]},{"code":"FR-1539","program":"pota","name":"Cote de Mancy Regional Reserve","coordinates":[5.54907,46.6575]},{"code":"FR-3911","program":"pota","name":"Reculees de la haute seille Natura 2000","coordinates":[5.65806,46.7278]},{"code":"FR-4435","program":"pota","name":"Reculee de la haute seille Natura 2000","coordinates":[5.66638,46.7278]},{"code":"FR-5165","program":"pota","name":"PELOUSE DE LA VIE D'ORGELET Biological Reserve","coordinates":[5.65021,46.5231]},{"code":"FR-5166","program":"pota","name":"PELOUSE EN RONDE Biological Reserve","coordinates":[5.63982,46.5179]},{"code":"FR-5168","program":"pota","name":"SUR LE DEVIAN Biological Reserve","coordinates":[5.57397,46.5053]},{"code":"FR-5389","program":"pota","name":"COMBE DE PRESILLY Biological Reserve","coordinates":[5.5935,46.5522]},{"code":"FR-5390","program":"pota","name":"EN CHAMARANDE Biological Reserve","coordinates":[5.60737,46.5495]},{"code":"FR-5391","program":"pota","name":"EN COUTHEREY Biological Reserve","coordinates":[5.66206,46.5425]},{"code":"FR-5396","program":"pota","name":"Grotte De Gravelle Biological Reserve","coordinates":[5.54054,46.6379]},{"code":"FR-5397","program":"pota","name":"GROTTE DE GRAVELLE 2 Biological Reserve","coordinates":[5.5404,46.6382]},{"code":"FR-5398","program":"pota","name":"RECULEE DE REVIGNY Biological Reserve","coordinates":[5.61195,46.6307]},{"code":"FR-5399","program":"pota","name":"COTE DE MANCY Biological Reserve","coordinates":[5.54618,46.6547]},{"code":"FR-5547","program":"pota","name":"SUR LA GRANDE ROCHE Biological Reserve","coordinates":[5.68911,46.5133]},{"code":"FR-5557","program":"pota","name":"EN VILLARET Biological Reserve","coordinates":[5.74705,46.5216]},{"code":"FR-5575","program":"pota","name":"LA COMBE D'AIN Biological Reserve","coordinates":[5.74415,46.635]},{"code":"FR-5682","program":"pota","name":"Faille de Chateau-Chalon Conservation Area","coordinates":[5.65,46.73]},{"code":"FR-5683","program":"pota","name":"PELOUSES SECHES DE BONNEFONTAINE Biological Reserve","coordinates":[5.73482,46.7361]},{"code":"FR-5684","program":"pota","name":"BOCAGE DE PIERRE DE LA MARRE Biological Reserve","coordinates":[5.71538,46.7374]},{"code":"FR-5687","program":"pota","name":"RECULEES DE LA HAUTE-SEILLE Biological Reserve","coordinates":[5.64877,46.7281]},{"code":"FR-5688","program":"pota","name":"Coupe Toarcien-Aalenien a Blois-sur-Seille Conservation Area","coordinates":[5.649,46.73]},{"code":"FR-5689","program":"pota","name":"FALAISES DE NEVY-SUR-SEILLE, BOIS DE ROCHE COTARD ET DE CHAPELLE VOLANT Biological Reserve","coordinates":[5.63576,46.7382]},{"code":"FR-5690","program":"pota","name":"Reculee de Baume-les-Messieurs Conservation Area","coordinates":[5.64,46.717]},{"code":"FR-5691","program":"pota","name":"PELOUSE, FALAISE ET EBOULIS DE SOUS LA BAUME Biological Reserve","coordinates":[5.63963,46.7151]},{"code":"FR-7770","program":"pota","name":"PONT DE LA PYLE Biological Reserve","coordinates":[5.67582,46.5157]},{"code":"FR-14607","program":"pota","name":"SUR FAHU Biological Reserve","coordinates":[5.748,46.655]},{"code":"FR-15190","program":"pota","name":"Lacs de Clairvaux Biological Reserve","coordinates":[5.749,46.564]},{"code":"FR-15191","program":"pota","name":"Pelouse de Beriat Biological Reserve","coordinates":[5.738,46.571]},{"code":"FR-15192","program":"pota","name":"Pelouses de l'echaud Biological Reserve","coordinates":[5.715,46.565]},{"code":"FR-15193","program":"pota","name":"Pelouses de sous France Biological Reserve","coordinates":[5.704,46.556]},{"code":"FR-15194","program":"pota","name":"Prairies humides de l'Achapt Biological Reserve","coordinates":[5.723,46.558]},{"code":"FR-15195","program":"pota","name":"Sous les carres Biological Reserve","coordinates":[5.723,46.549]},{"code":"FR-15196","program":"pota","name":"Bocage sur le mont Biological Reserve","coordinates":[5.694,46.538]},{"code":"FR-15197","program":"pota","name":"Sur signoge Biological Reserve","coordinates":[5.71,46.534]},{"code":"FR-15198","program":"pota","name":"Sur les roches Biological Reserve","coordinates":[5.72,46.537]},{"code":"F/JU-072","program":"sota","name":"Bois du Crotard","coordinates":[5.5758,46.5731]},{"code":"F/JU-073","program":"sota","name":"Côte Bastien, Marnézia","coordinates":[5.6524,46.5777]}]}