{"lat":46.75,"lon":-122.25,"programs":["pota","sota"],"count":10,"references":[{"code":"US-5568","program":"pota","name":"Elbe Hills-Tahoma State Forest","coordinates":[-122.094,46.7852]},{"code":"W7W/RS-057","program":"sota","name":"Puyallup Lookout","coordinates":[-122.0172,46.8341]},{"code":"W7W/RS-060","program":"sota","name":"The Divide","coordinates":[-122.0676,46.8895]},{"code":"W7W/RS-061","program":"sota","name":"Wild Benchmark","coordinates":[-122.067,46.8219]},{"code":"W7W/RS-062","program":"sota","name":"3460 F-Layer Pk","coordinates":[-122.0736,46.8559]},{"code":"W7W/RS-063","program":"sota","name":"3220 End Fed Hill","coordinates":[-122.17,46.7935]},{"code":"W7W/RS-064","program":"sota","name":"Saint Paul Lookout","coordinates":[-122.0797,46.928]},{"code":"W7W/RS-066","program":"sota","name":"Ohop Benchmark","coordinates":[-122.2186,46.9002]},{"code":"W7W/RS-067","program":"sota","name":"Alder Benchmark","coordinates":[-122.2385,46.7933]},{"code":"W7W/SO-076","program":"sota","name":"2060 Lower Sideband Pk","coordinates":[-122.2418,46.7689]}]}