{"lat":48.25,"lon":-71,"programs":["pota","wwbota"],"count":5,"references":[{"code":"CA-1937","program":"pota","name":"Battures-de-Saint-Fulgence Wildlife Refuge","coordinates":[-70.9157,48.4524]},{"code":"CA-4949","program":"pota","name":"Parc Aventures Cap Jaseux Regional Park","coordinates":[-70.8204,48.426]},{"code":"CA-4981","program":"pota","name":"Rivière-à-Mars (Passe à Saumons) Regional Park","coordinates":[-70.907,48.327]},{"code":"CA-5853","program":"pota","name":"Alert Hangar National Historic Site","coordinates":[-70.9722,48.3344]},{"code":"B/CA-1404","program":"wwbota","name":"FRP ED3","coordinates":[-70.9876496,48.33933193]}]}