{"lat":48.5,"lon":-118.25,"programs":["pota","sota"],"count":10,"references":[{"code":"US-0699","program":"pota","name":"Lake Roosevelt National Recreation Area","coordinates":[-118.113,48.5863]},{"code":"US-12243","program":"pota","name":"Sherman Creek Wildlife Area State Fish and Wildlife Area","coordinates":[-118.138,48.6083]},{"code":"W7W/FR-044","program":"sota","name":"Hoodoo Mountain","coordinates":[-118.2393,48.653]},{"code":"W7W/FR-072","program":"sota","name":"4455 Mt J-Pole","coordinates":[-118.2063,48.6688]},{"code":"W7W/FR-097","program":"sota","name":"Bangs Mountain","coordinates":[-118.2211,48.5668]},{"code":"W7W/FR-128","program":"sota","name":"Bald Hill","coordinates":[-118.2286,48.513]},{"code":"W7W/ST-115","program":"sota","name":"Kelly Hill","coordinates":[-118.0733,48.7239]},{"code":"W7W/ST-116","program":"sota","name":"Gold Hill","coordinates":[-118.0297,48.6291]},{"code":"W7W/ST-131","program":"sota","name":"2970 Kilohertz Hill","coordinates":[-118.0311,48.6619]},{"code":"W7W/ST-148","program":"sota","name":"4620","coordinates":[-118.0071,48.519]}]}