{"lat":51.75,"lon":15.25,"programs":["pota"],"count":6,"references":[{"code":"PL-1952","program":"pota","name":"Broniszów Natura 2000","coordinates":[15.4661,51.7909]},{"code":"PL-1959","program":"pota","name":"Nowogrodzkie Przygiełkowisko Natura 2000","coordinates":[15.283,51.8133]},{"code":"PL-2658","program":"pota","name":"Dolina Śląskiej Ochli Protected Landscape Area","coordinates":[15.4547,51.865]},{"code":"PL-2659","program":"pota","name":"Liliowy Las Nature and Landscape Complex","coordinates":[15.4889,51.9036]},{"code":"PL-2660","program":"pota","name":"Wzniesienia Zielonogórskie Protected Landscape Area","coordinates":[15.3916,51.9198]},{"code":"PL-2790","program":"pota","name":"Brekinie koło Broniszowa Nature Reserve","coordinates":[15.4491,51.788]}]}