{"lat":52.25,"lon":19.5,"programs":["pota"],"count":17,"references":[{"code":"PL-1015","program":"pota","name":"Dolina Przysowy i Słudwi Natura 2000","coordinates":[19.6827,52.2843]},{"code":"PL-1016","program":"pota","name":"Dolina Przysowy Protected Landscape Area","coordinates":[19.643,52.3025]},{"code":"PL-1034","program":"pota","name":"Gostynińsko-Gąbiński Protected Landscape Area","coordinates":[19.722,52.4547]},{"code":"PL-1040","program":"pota","name":"Jezioro Zdworskie Nature and Landscape Complex","coordinates":[19.6863,52.4358]},{"code":"PL-1050","program":"pota","name":"Jezioro Ciechomickie Nature and Landscape Complex","coordinates":[19.6731,52.4682]},{"code":"PL-1059","program":"pota","name":"Jezioro Górskie Nature and Landscape Complex","coordinates":[19.6509,52.48]},{"code":"PL-1065","program":"pota","name":"Korzeń Nature Reserve","coordinates":[19.6367,52.4431]},{"code":"PL-1066","program":"pota","name":"Dąbrowa Łącka Nature Reserve","coordinates":[19.6386,52.4631]},{"code":"PL-1072","program":"pota","name":"Uroczyska Łąckie Natura 2000","coordinates":[19.6279,52.49]},{"code":"PL-1074","program":"pota","name":"Jezioro Łąckie Duże Nature and Landscape Complex","coordinates":[19.6245,52.4648]},{"code":"PL-1081","program":"pota","name":"Łąck Nature Reserve","coordinates":[19.6089,52.4911]},{"code":"PL-1089","program":"pota","name":"Jezioro Szczawińskie Nature Reserve","coordinates":[19.569,52.3637]},{"code":"PL-1100","program":"pota","name":"Jezioro Drzezno Nature Reserve","coordinates":[19.5422,52.4885]},{"code":"PL-1109","program":"pota","name":"Jezioro Sumino Nature and Landscape Complex","coordinates":[19.5236,52.4824]},{"code":"PL-1113","program":"pota","name":"Jezioro Białe Nature and Landscape Complex","coordinates":[19.5134,52.4924]},{"code":"PL-1115","program":"pota","name":"Osetnica Nature Reserve","coordinates":[19.506,52.4109]},{"code":"PL-2932","program":"pota","name":"Drzesno Natura 2000","coordinates":[19.5539,52.4869]}]}