{"lat":53,"lon":-6.5,"programs":["pota","sota"],"count":10,"references":[{"code":"IE-0003","program":"pota","name":"Wicklow Mountains National Park","coordinates":[-6.31222,53.1479]},{"code":"IE-0097","program":"pota","name":"Glendalough Park Nature Reserve","coordinates":[-6.34616,53.0057]},{"code":"IE-0117","program":"pota","name":"Tibradden Wood National Forest","coordinates":[-6.2949,53.2429]},{"code":"IE-0118","program":"pota","name":"Cruagh Wood National Forest","coordinates":[-6.31163,53.2421]},{"code":"EI/IE-002","program":"sota","name":"Mullaghcleevaun","coordinates":[-6.406681,53.103596]},{"code":"EI/IE-003","program":"sota","name":"Tonelagee","coordinates":[-6.382647,53.053436]},{"code":"EI/IE-005","program":"sota","name":"Kippure","coordinates":[-6.332091,53.1782]},{"code":"EI/IE-012","program":"sota","name":"Scarr","coordinates":[-6.312482,53.055157]},{"code":"EI/IE-014","program":"sota","name":"Sorrel Hill","coordinates":[-6.443062,53.147587]},{"code":"EI/IE-044","program":"sota","name":"Saggart Hill","coordinates":[-6.477666,53.24678]}]}