{"lat":58,"lon":-134,"programs":["sota"],"count":27,"references":[{"code":"KLS/JU-195","program":"sota","name":"5321","coordinates":[-133.922,58.2214]},{"code":"KLS/JU-209","program":"sota","name":"5193","coordinates":[-133.8633,58.2092]},{"code":"KLS/JU-213","program":"sota","name":"5170","coordinates":[-133.9849,58.1918]},{"code":"KLS/JU-219","program":"sota","name":"5150","coordinates":[-133.9308,58.2031]},{"code":"KLS/JU-222","program":"sota","name":"Cherry Benchmark","coordinates":[-133.9331,58.1539]},{"code":"KLS/JU-227","program":"sota","name":"5050","coordinates":[-133.9002,58.1382]},{"code":"KLS/JU-228","program":"sota","name":"5050","coordinates":[-133.9384,58.2378]},{"code":"KLS/JU-236","program":"sota","name":"4953","coordinates":[-133.7881,58.1597]},{"code":"KLS/JU-237","program":"sota","name":"4950","coordinates":[-133.8723,58.1548]},{"code":"KLS/JU-251","program":"sota","name":"4850","coordinates":[-133.8601,58.2415]},{"code":"KLS/JU-257","program":"sota","name":"4842","coordinates":[-133.9988,58.2122]},{"code":"KLS/JU-268","program":"sota","name":"4673","coordinates":[-133.8163,58.1039]},{"code":"KLS/JU-301","program":"sota","name":"4319","coordinates":[-133.79,58.217]},{"code":"KLS/JU-304","program":"sota","name":"4290","coordinates":[-133.8488,58.1129]},{"code":"KLS/JU-327","program":"sota","name":"3950","coordinates":[-133.8166,58.1545]},{"code":"KLS/JU-328","program":"sota","name":"3945","coordinates":[-133.7957,58.1173]},{"code":"KLS/JU-332","program":"sota","name":"3850","coordinates":[-133.9427,58.0714]},{"code":"KLS/JU-336","program":"sota","name":"Everett Peak","coordinates":[-133.9055,58.0066]},{"code":"KLS/JU-339","program":"sota","name":"3750","coordinates":[-133.9166,58.0985]},{"code":"KLS/JU-344","program":"sota","name":"Arthur Peak","coordinates":[-133.9783,58.0526]},{"code":"KLS/JU-345","program":"sota","name":"3646","coordinates":[-133.9188,58.0647]},{"code":"KLS/JU-347","program":"sota","name":"3579","coordinates":[-133.9524,58.0675]},{"code":"KLS/JU-352","program":"sota","name":"3454","coordinates":[-133.9301,58.0766]},{"code":"KLS/JU-361","program":"sota","name":"3190","coordinates":[-133.8686,58.02]},{"code":"KLS/JU-370","program":"sota","name":"2950","coordinates":[-133.8667,58.0434]},{"code":"KLS/JU-371","program":"sota","name":"2950","coordinates":[-133.9613,58.1147]},{"code":"KLS/JU-373","program":"sota","name":"2850","coordinates":[-133.8459,58.0139]}]}