{"lat":59.5,"lon":17.25,"programs":["pota"],"count":10,"references":[{"code":"SE-0758","program":"pota","name":"Wik Natura 2000","coordinates":[17.4743,59.7378]},{"code":"SE-1042","program":"pota","name":"Biskops-Arnö Natura 2000","coordinates":[17.4872,59.6641]},{"code":"SE-1045","program":"pota","name":"Nybylund Natura 2000","coordinates":[17.4759,59.6763]},{"code":"SE-1046","program":"pota","name":"Nybylund Nature Reserve","coordinates":[17.4685,59.678]},{"code":"SE-1050","program":"pota","name":"Hjälstaviken Natura 2000","coordinates":[17.3907,59.6848]},{"code":"SE-1051","program":"pota","name":"Hjälstaviken Nature Reserve","coordinates":[17.3679,59.658]},{"code":"SE-1052","program":"pota","name":"Signalberget Nature Reserve","coordinates":[17.2787,59.7355]},{"code":"SE-1053","program":"pota","name":"Uvberget Natura 2000","coordinates":[17.2788,59.745]},{"code":"SE-1111","program":"pota","name":"Kalmarnäslandet Nature Reserve","coordinates":[17.4463,59.5547]},{"code":"SE-1112","program":"pota","name":"Kalmarnäs Natura 2000","coordinates":[17.4508,59.5497]}]}