{"lat":60.75,"lon":-147.25,"programs":["sota"],"count":7,"references":[{"code":"KLA/VW-772","program":"sota","name":"1654","coordinates":[-147.1463,60.858]},{"code":"KLA/VW-789","program":"sota","name":"1558","coordinates":[-147.239,60.8941]},{"code":"KLA/VW-813","program":"sota","name":"1407","coordinates":[-147.0971,60.8792]},{"code":"KLA/VW-820","program":"sota","name":"1365","coordinates":[-147.1521,60.8865]},{"code":"KLA/VW-827","program":"sota","name":"1319","coordinates":[-147.1271,60.8659]},{"code":"KLA/VW-831","program":"sota","name":"1280","coordinates":[-147.1699,60.8646]},{"code":"KLA/VW-844","program":"sota","name":"1150","coordinates":[-147.183,60.8871]}]}