{"lat":61.5,"lon":5.5,"programs":["pota","sota"],"count":17,"references":[{"code":"NO-0191","program":"pota","name":"Bogane Nature Reserve","coordinates":[5.61462,61.636]},{"code":"NO-0205","program":"pota","name":"Brandatjørna Nature Reserve","coordinates":[5.61378,61.6122]},{"code":"NO-0326","program":"pota","name":"Eikevolltjønnmyra Nature Reserve","coordinates":[5.52634,61.5734]},{"code":"NO-0617","program":"pota","name":"Grønøyra Nature Reserve","coordinates":[5.72235,61.5083]},{"code":"NO-1293","program":"pota","name":"Mallasvika Nature Reserve","coordinates":[5.69203,61.5067]},{"code":"NO-2875","program":"pota","name":"Eimhjellen Nature Reserve","coordinates":[5.72475,61.6141]},{"code":"LA/SF-226","program":"sota","name":"Ålfotbreen Punkt på","coordinates":[5.6365,61.7417]},{"code":"LA/SF-291","program":"sota","name":"Trollebotsnipa, (Storebotsnipa)","coordinates":[5.5062,61.7154]},{"code":"LA/SF-294","program":"sota","name":"Blåbrevatnet vest for","coordinates":[5.5361,61.7499]},{"code":"LA/SF-342","program":"sota","name":"Skorfjellet, (Kaldevassnykane)","coordinates":[5.6983,61.6965]},{"code":"LA/SF-345","program":"sota","name":"Lassenipa","coordinates":[5.6141,61.6887]},{"code":"LA/SF-358","program":"sota","name":"Midbønipa","coordinates":[5.5575,61.6459]},{"code":"LA/SF-410","program":"sota","name":"Steindalsfjellet","coordinates":[5.5226,61.5348]},{"code":"LA/SF-412","program":"sota","name":"Eggene","coordinates":[5.7144,61.6538]},{"code":"LA/SF-414","program":"sota","name":"Blåfjellet","coordinates":[5.5701,61.5118]},{"code":"LA/SF-424","program":"sota","name":"Ramsdalsnipa, (Solheimsnipa)","coordinates":[5.7059,61.559]},{"code":"LA/SF-434","program":"sota","name":"Bolteheia","coordinates":[5.7133,61.5445]}]}