{"lat":61.5,"lon":-134.25,"programs":["sota"],"count":15,"references":[{"code":"VY1/LL-012","program":"sota","name":"VY1/LL-012","coordinates":[-134.0325,61.6935]},{"code":"VY1/LL-014","program":"sota","name":"Mount D'Abbadie","coordinates":[-134.0971,61.7102]},{"code":"VY1/LL-015","program":"sota","name":"VY1/LL-015","coordinates":[-134.0608,61.7008]},{"code":"VY1/LL-019","program":"sota","name":"VY1/LL-019","coordinates":[-134.0219,61.7206]},{"code":"VY1/LL-022","program":"sota","name":"VY1/LL-022","coordinates":[-134.0404,61.739]},{"code":"VY1/LL-023","program":"sota","name":"VY1/LL-023","coordinates":[-134.0054,61.7431]},{"code":"VY1/LL-025","program":"sota","name":"VY1/LL-025","coordinates":[-134.0277,61.6717]},{"code":"VY1/LL-028","program":"sota","name":"VY1/LL-028","coordinates":[-134.1019,61.6904]},{"code":"VY1/LL-030","program":"sota","name":"VY1/LL-030","coordinates":[-134.0523,61.6073]},{"code":"VY1/LL-031","program":"sota","name":"Last Peak","coordinates":[-134.2202,61.5965]},{"code":"VY1/LL-036","program":"sota","name":"VY1/LL-036","coordinates":[-134.084,61.5975]},{"code":"VY1/LL-038","program":"sota","name":"VY1/LL-038","coordinates":[-134.2429,61.6902]},{"code":"VY1/LL-044","program":"sota","name":"VY1/LL-044","coordinates":[-134.0611,61.646]},{"code":"VY1/LL-048","program":"sota","name":"Semenhof Hills","coordinates":[-134.194,61.6256]},{"code":"VY1/LL-051","program":"sota","name":"VY1/LL-051","coordinates":[-134.1931,61.7281]}]}