{"lat":62.25,"lon":-150,"programs":["sota"],"count":8,"references":[{"code":"KLA/MC-568","program":"sota","name":"Bald Mountain","coordinates":[-149.7542,62.3083]},{"code":"KLA/MC-586","program":"sota","name":"2550","coordinates":[-149.8083,62.4774]},{"code":"KLA/MC-587","program":"sota","name":"2480","coordinates":[-149.7747,62.4879]},{"code":"KLA/MC-589","program":"sota","name":"2350","coordinates":[-149.7607,62.46]},{"code":"KLA/MC-594","program":"sota","name":"1850","coordinates":[-149.7988,62.432]},{"code":"KLA/MC-595","program":"sota","name":"1850","coordinates":[-149.8122,62.42]},{"code":"KLA/MC-597","program":"sota","name":"1750","coordinates":[-149.9399,62.4385]},{"code":"KLA/MC-598","program":"sota","name":"1550","coordinates":[-149.852,62.4097]}]}