{"lat":68.5,"lon":16.75,"programs":["pota","sota"],"count":8,"references":[{"code":"NO-0092","program":"pota","name":"Balteskardvatnet Nature Reserve","coordinates":[16.9883,68.6632]},{"code":"LA/NL-257","program":"sota","name":"Litletinden","coordinates":[16.9288,68.551]},{"code":"LA/NL-477","program":"sota","name":"Mersskartinden","coordinates":[16.8255,68.5501]},{"code":"LA/TR-107","program":"sota","name":"Skittendalstinden","coordinates":[16.9542,68.5789]},{"code":"LA/TR-193","program":"sota","name":"Lafjelltind","coordinates":[16.9365,68.6282]},{"code":"LA/TR-200","program":"sota","name":"Rismålstinden","coordinates":[16.867,68.5728]},{"code":"LA/TR-237","program":"sota","name":"Blåfjellet","coordinates":[16.8505,68.6162]},{"code":"LA/TR-308","program":"sota","name":"Svellen","coordinates":[16.9987,68.7009]}]}