{"lat":68.5,"lon":-144.25,"programs":["sota"],"count":16,"references":[{"code":"KLF/ME-157","program":"sota","name":"6942","coordinates":[-144.245,68.6689]},{"code":"KLF/ME-162","program":"sota","name":"6852","coordinates":[-144.148,68.6388]},{"code":"KLF/ME-184","program":"sota","name":"6738","coordinates":[-144.2436,68.5768]},{"code":"KLF/ME-237","program":"sota","name":"6443","coordinates":[-144.143,68.5011]},{"code":"KLF/ME-240","program":"sota","name":"6410","coordinates":[-144.1873,68.6306]},{"code":"KLF/ME-257","program":"sota","name":"6270","coordinates":[-144.2139,68.6029]},{"code":"KLF/ME-292","program":"sota","name":"6082","coordinates":[-144.2351,68.5467]},{"code":"KLF/ME-320","program":"sota","name":"5944","coordinates":[-144.165,68.6631]},{"code":"KLF/ME-384","program":"sota","name":"5582","coordinates":[-144.1259,68.5661]},{"code":"KLF/ME-393","program":"sota","name":"5552","coordinates":[-144.0253,68.5799]},{"code":"KLF/ME-423","program":"sota","name":"5444","coordinates":[-144.1315,68.5891]},{"code":"KLF/ME-449","program":"sota","name":"5250","coordinates":[-144.0018,68.7288]},{"code":"KLF/ME-458","program":"sota","name":"5203","coordinates":[-144.0623,68.6805]},{"code":"KLF/ME-482","program":"sota","name":"5030","coordinates":[-144.0603,68.5878]},{"code":"KLF/ME-492","program":"sota","name":"4950","coordinates":[-144.0035,68.6323]},{"code":"KLF/ME-606","program":"sota","name":"4050","coordinates":[-144.0265,68.538]}]}